quizr/__init__.py
quizr/__main__.py
quizr/cli.py
quizr/config.py
quizr/data_manager.py
quizr/models.py
quizr/quiz_engine.py
quizr_cli-1.0.0.dist-info/licenses/LICENSE.txt
quizr_cli-1.0.0.dist-info/licenses/license.Conflict.txt
quizr_cli-1.0.0.dist-info/METADATA
quizr_cli-1.0.0.dist-info/WHEEL
quizr_cli-1.0.0.dist-info/entry_points.txt
quizr_cli-1.0.0.dist-info/top_level.txt
quizr_cli-1.0.0.dist-info/RECORD
