Metadata-Version: 2.4
Name: quizr-cli
Version: 1.0.0
Summary: A command-line quiz tool with spaced repetition
Home-page: https://github.com/sipistab/QUIZR
Author: QUIZR Team
Author-email: sipistab@gmail.com
Project-URL: Bug Tracker, https://github.com/sipistab/QUIZR/issues
Project-URL: Documentation, https://github.com/sipistab/QUIZR#readme
Keywords: quiz,learning,spaced-repetition,education,cli
Classifier: Development Status :: 4 - Beta
Classifier: Environment :: Console
Classifier: Intended Audience :: Education
Classifier: License :: CC0 1.0 Universal (CC0 1.0) Public Domain Dedication
Classifier: Operating System :: OS Independent
Classifier: Programming Language :: Python :: 3
Classifier: Programming Language :: Python :: 3.7
Classifier: Programming Language :: Python :: 3.8
Classifier: Programming Language :: Python :: 3.9
Classifier: Programming Language :: Python :: 3.10
Classifier: Topic :: Education
Classifier: Topic :: Education :: Testing
Requires-Python: >=3.7
License-File: LICENSE.txt
License-File: license.Conflict.txt
Requires-Dist: PyYAML>=6.0
Requires-Dist: click>=8.0.0
Requires-Dist: fuzzywuzzy>=0.18.0
Requires-Dist: python-Levenshtein>=0.12.0
Dynamic: author
Dynamic: author-email
Dynamic: classifier
Dynamic: description
Dynamic: description-content-type
Dynamic: home-page
Dynamic: keywords
Dynamic: license-file
Dynamic: project-url
Dynamic: requires-dist
Dynamic: requires-python
Dynamic: summary
